licheck/__init__.py
licheck/__main__.py
licheck/api.py
licheck/cli.py
licheck/constants.py
licheck/exceptions.py
licheck-1.0.0.dist-info/LICENSE.txt
licheck-1.0.0.dist-info/METADATA
licheck-1.0.0.dist-info/WHEEL
licheck-1.0.0.dist-info/entry_points.txt
licheck-1.0.0.dist-info/top_level.txt
licheck-1.0.0.dist-info/RECORD
