Metadata-Version: 2.1
Name: licheck
Version: 1.0.0
Summary: Automatically check the licenses of package dependencies.
Home-page: https://blog.franco.net.eu.org/software/#licheck
Author: Franco Masotti
Author-email: franco.masotti@tutanota.com
License: GPL
Keywords: text license
Platform: UNKNOWN
Classifier: Development Status :: 3 - Alpha
Classifier: Topic :: Utilities
Classifier: Intended Audience :: End Users/Desktop
Classifier: Environment :: Console
Classifier: License :: OSI Approved :: GNU General Public License v3 or later (GPLv3+)
Classifier: Programming Language :: Python :: 3
Requires-Python: >=3.5, <4
License-File: LICENSE.txt
Requires-Dist: PyYAML (<7,>=6)
Requires-Dist: tabulate (<1,>=0)
Requires-Dist: appdirs (<2,>=1)
Requires-Dist: requests (<2.27,>=2.26)
